openstuder.py
openstuder_client-0.6.2.dist-info/LICENSE
openstuder_client-0.6.2.dist-info/METADATA
openstuder_client-0.6.2.dist-info/WHEEL
openstuder_client-0.6.2.dist-info/top_level.txt
openstuder_client-0.6.2.dist-info/RECORD
