Metadata-Version: 2.1
Name: openstuder-client
Version: 0.6.2
Summary: Python client to connect to OpenStuder gateway via WebSocket or Bluetooth
Home-page: http://openstuder.github.io
Author: Michael Clausen
Author-email: michael.clausen@hevs.ch
License: UNKNOWN
Platform: UNKNOWN
Classifier: Programming Language :: Python :: 3
Classifier: License :: OSI Approved :: MIT License
Classifier: Operating System :: OS Independent
Requires-Python: >=3.7
License-File: LICENSE
Requires-Dist: websocket-client (==1.3.1)
Requires-Dist: cbor2 (==5.4.2.post1)
Requires-Dist: bleak (==0.14.2)
